Metadata-Version: 2.1
Name: mixingbear
Version: 0.0.1
Summary: Automatic beat-mixing of music files
Home-page: https://github.com/dodiku/MixingBear
Author: Dror Ayalon
Author-email: d.stamail@gmail.com
License: MIT
Keywords: Automatic beat-mixing of music files. audio analysis
Platform: UNKNOWN
Classifier: Development Status :: 4 - Beta
Classifier: License :: OSI Approved :: MIT License
Classifier: Programming Language :: Python :: 3.6
Classifier: Topic :: Multimedia :: Sound/Audio :: Mixers
